<?xml version="1.0" encoding="UTF-8"?>
<?xml-stylesheet href="CoreNLP-to-HTML.xsl" type="text/xsl"?>
<root>
  <document>
    <sentences>
      <sentence id="1">
        <tokens>
          <token id="1">
            <word>Hola</word>
            <CharacterOffsetBegin>0</CharacterOffsetBegin>
            <CharacterOffsetEnd>4</CharacterOffsetEnd>
            <POS>i</POS>
            <NER>PERS</NER>
          </token>
          <token id="2">
            <word>,</word>
            <CharacterOffsetBegin>4</CharacterOffsetBegin>
            <CharacterOffsetEnd>5</CharacterOffsetEnd>
            <POS>fc</POS>
            <NER>O</NER>
          </token>
          <token id="3">
            <word>como</word>
            <CharacterOffsetBegin>6</CharacterOffsetBegin>
            <CharacterOffsetEnd>10</CharacterOffsetEnd>
            <POS>cs</POS>
            <NER>O</NER>
          </token>
          <token id="4">
            <word>estas</word>
            <CharacterOffsetBegin>11</CharacterOffsetBegin>
            <CharacterOffsetEnd>16</CharacterOffsetEnd>
            <POS>dd0000</POS>
            <NER>O</NER>
          </token>
          <token id="5">
            <word>?</word>
            <CharacterOffsetBegin>16</CharacterOffsetBegin>
            <CharacterOffsetEnd>17</CharacterOffsetEnd>
            <POS>fit</POS>
            <NER>O</NER>
          </token>
        </tokens>
        <parse>(ROOT (sentence (i Hola) (sn (grup.nom (sp (fc ,) (prep (cs como)) (sn (spec (dd0000 estas)))))) (fit ?))) </parse>
      </sentence>
      <sentence id="2">
        <tokens>
          <token id="1">
            <word>Me</word>
            <CharacterOffsetBegin>18</CharacterOffsetBegin>
            <CharacterOffsetEnd>20</CharacterOffsetEnd>
            <POS>pp000000</POS>
            <NER>O</NER>
          </token>
          <token id="2">
            <word>llamo</word>
            <CharacterOffsetBegin>21</CharacterOffsetBegin>
            <CharacterOffsetEnd>26</CharacterOffsetEnd>
            <POS>vmip000</POS>
            <NER>O</NER>
          </token>
          <token id="3">
            <word>Alejandro</word>
            <CharacterOffsetBegin>27</CharacterOffsetBegin>
            <CharacterOffsetEnd>36</CharacterOffsetEnd>
            <POS>np00000</POS>
            <NER>PERS</NER>
          </token>
          <token id="4">
            <word>.</word>
            <CharacterOffsetBegin>36</CharacterOffsetBegin>
            <CharacterOffsetEnd>37</CharacterOffsetEnd>
            <POS>fp</POS>
            <NER>O</NER>
          </token>
        </tokens>
        <parse>(ROOT (sentence (S (sn (grup.nom (pp000000 Me))) (grup.verb (vmip000 llamo)) (sn (grup.nom (np00000 Alejandro)))) (fp .))) </parse>
      </sentence>
      <sentence id="3">
        <tokens>
          <token id="1">
            <word>Ellos</word>
            <CharacterOffsetBegin>38</CharacterOffsetBegin>
            <CharacterOffsetEnd>43</CharacterOffsetEnd>
            <POS>pp000000</POS>
            <NER>O</NER>
          </token>
          <token id="2">
            <word>se</word>
            <CharacterOffsetBegin>44</CharacterOffsetBegin>
            <CharacterOffsetEnd>46</CharacterOffsetEnd>
            <POS>p0000000</POS>
            <NER>O</NER>
          </token>
          <token id="3">
            <word>llaman</word>
            <CharacterOffsetBegin>47</CharacterOffsetBegin>
            <CharacterOffsetEnd>53</CharacterOffsetEnd>
            <POS>vmip000</POS>
            <NER>O</NER>
          </token>
          <token id="4">
            <word>Eric</word>
            <CharacterOffsetBegin>54</CharacterOffsetBegin>
            <CharacterOffsetEnd>58</CharacterOffsetEnd>
            <POS>np00000</POS>
            <NER>PERS</NER>
          </token>
          <token id="5">
            <word>,</word>
            <CharacterOffsetBegin>58</CharacterOffsetBegin>
            <CharacterOffsetEnd>59</CharacterOffsetEnd>
            <POS>fc</POS>
            <NER>O</NER>
          </token>
          <token id="6">
            <word>Pearson</word>
            <CharacterOffsetBegin>60</CharacterOffsetBegin>
            <CharacterOffsetEnd>67</CharacterOffsetEnd>
            <POS>np00000</POS>
            <NER>PERS</NER>
          </token>
          <token id="7">
            <word>,</word>
            <CharacterOffsetBegin>67</CharacterOffsetBegin>
            <CharacterOffsetEnd>68</CharacterOffsetEnd>
            <POS>fc</POS>
            <NER>O</NER>
          </token>
          <token id="8">
            <word>y</word>
            <CharacterOffsetBegin>69</CharacterOffsetBegin>
            <CharacterOffsetEnd>70</CharacterOffsetEnd>
            <POS>cc</POS>
            <NER>O</NER>
          </token>
          <token id="9">
            <word>Gideon</word>
            <CharacterOffsetBegin>71</CharacterOffsetBegin>
            <CharacterOffsetEnd>77</CharacterOffsetEnd>
            <POS>np00000</POS>
            <NER>PERS</NER>
          </token>
          <token id="10">
            <word>.</word>
            <CharacterOffsetBegin>77</CharacterOffsetBegin>
            <CharacterOffsetEnd>78</CharacterOffsetEnd>
            <POS>fp</POS>
            <NER>O</NER>
          </token>
        </tokens>
        <parse>(ROOT (sentence (S (morfema.pronominal (pp000000 Ellos)) (sn (grup.nom (p0000000 se))) (grup.verb (vmip000 llaman)) (sn (grup.nom (grup.nom (np00000 Eric)) (fc ,) (grup.nom (np00000 Pearson))) (fc ,))) (conj (cc y)) (S (sn (grup.nom (np00000 Gideon)))) (fp .))) </parse>
      </sentence>
    </sentences>
  </document>
</root>
